onnxruntime_easy/__init__.py
onnxruntime_easy-0.0.3.dist-info/licenses/LICENSE
onnxruntime_easy-0.0.3.dist-info/METADATA
onnxruntime_easy-0.0.3.dist-info/WHEEL
onnxruntime_easy-0.0.3.dist-info/top_level.txt
onnxruntime_easy-0.0.3.dist-info/RECORD
