Metadata-Version: 2.4
Name: onnxruntime-easy
Version: 0.0.3
Summary: Simplified APIs for onnxruntime
Author-email: Justin Chu <justinchuby@users.noreply.github.com>
Project-URL: Documentation, https://github.com/justinchuby/onnxruntime-easy#readme
Project-URL: Issues, https://github.com/justinchuby/onnxruntime-easy/issues
Project-URL: Source, https://github.com/justinchuby/onnxruntime-easy
Classifier: Development Status :: 3 - Alpha
Classifier: Environment :: Console
Classifier: Intended Audience :: Developers
Classifier: Operating System :: POSIX
Classifier: Operating System :: MacOS :: MacOS X
Classifier: Operating System :: Microsoft :: Windows
Classifier: Programming Language :: Python :: 3
Classifier: License :: OSI Approved :: MIT License
Requires-Python: >=3.9
License-File: LICENSE
Requires-Dist: numpy
Requires-Dist: onnxruntime>=1.18.0
Dynamic: license-file
